{
  "scan_timestamp": "2026-01-12T11:28:34.675230+00:00",
  "duration_seconds": 1027.02,
  "performance_metrics": {
    "total_processed": 470,
    "valid_configs": 317,
    "duplicates": 0,
    "failed_tests": 153,
    "success_rate": 67.45,
    "avg_latency_ms": 114.2,
    "avg_score": 99.24
  },
  "protocol_summary": {
    "vmess": {
      "count": 95,
      "avg_lat": 71.78947368421052,
      "avg_score": 99.52140350877193
    },
    "vless": {
      "count": 138,
      "avg_lat": 109.69565217391305,
      "avg_score": 99.26869565217392
    },
    "ss": {
      "count": 0,
      "avg_lat": 0.0,
      "avg_score": 0.0
    },
    "trojan": {
      "count": 84,
      "avg_lat": 169.57142857142858,
      "avg_score": 98.86952380952383
    }
  }
}